[{"id":5751,"modifiedDate":"2020-08-27T14:25:01","fileModifiedDate":"2022-10-20T17:37:12.6276717-04:00","fileCreatedDate":"2022-10-18T13:02:14.9806458-04:00","filePath":"D:/Unity/Unity Projects/Control Room URP/Assets/GameDevHQ/FileBase/Extensions/Systems/Utilities/Replace_With_Prefab"},{"id":3435,"modifiedDate":"2021-12-31T00:54:31","fileModifiedDate":"2022-10-20T17:37:29.3796152-04:00","fileCreatedDate":"2022-10-18T13:02:14.9753485-04:00","filePath":"D:/Unity/Unity Projects/Control Room URP/Assets/GameDevHQ/FileBase/3D/Environments/Sci-Fi/Scifi_Terminal_08"},{"id":3429,"modifiedDate":"2021-12-31T00:54:50","fileModifiedDate":"2022-10-20T17:37:29.4803462-04:00","fileCreatedDate":"2022-10-18T13:02:14.9773498-04:00","filePath":"D:/Unity/Unity Projects/Control Room URP/Assets/GameDevHQ/FileBase/3D/Environments/Sci-Fi/Scifi_Terminal_09"},{"id":3426,"modifiedDate":"2021-12-31T00:54:56","fileModifiedDate":"2022-10-20T17:37:29.5322444-04:00","fileCreatedDate":"2022-10-18T13:02:14.977924-04:00","filePath":"D:/Unity/Unity Projects/Control Room URP/Assets/GameDevHQ/FileBase/3D/Environments/Sci-Fi/Scifi_Testtube_03"},{"id":3423,"modifiedDate":"2021-12-31T00:55:34","fileModifiedDate":"2022-10-20T17:37:29.5832364-04:00","fileCreatedDate":"2022-10-18T13:02:14.9737707-04:00","filePath":"D:/Unity/Unity Projects/Control Room URP/Assets/GameDevHQ/FileBase/3D/Environments/Sci-Fi/Scifi_Terminal_07"},{"id":1304,"modifiedDate":"2021-12-31T01:01:16","fileModifiedDate":"2022-10-20T17:38:04.7511659-04:00","fileCreatedDate":"2022-10-18T13:02:14.9792799-04:00","filePath":"D:/Unity/Unity Projects/Control Room URP/Assets/GameDevHQ/FileBase/3D/Environments/Sci-Fi/Scifi_Walls_08_10"},{"id":1301,"modifiedDate":"2021-12-31T01:01:22","fileModifiedDate":"2022-10-20T17:38:04.8013561-04:00","fileCreatedDate":"2022-10-18T13:02:14.9786087-04:00","filePath":"D:/Unity/Unity Projects/Control Room URP/Assets/GameDevHQ/FileBase/3D/Environments/Sci-Fi/Scifi_Walls_05_07"},{"id":1274,"modifiedDate":"2021-12-31T01:10:51","fileModifiedDate":"2022-10-20T17:38:05.2703571-04:00","fileCreatedDate":"2022-10-18T13:02:14.972774-04:00","filePath":"D:/Unity/Unity Projects/Control Room URP/Assets/GameDevHQ/FileBase/3D/Environments/Sci-Fi/Scifi_Stair_01_02"},{"id":1199,"modifiedDate":"2021-12-31T01:14:09","fileModifiedDate":"2022-10-20T17:38:06.6029979-04:00","fileCreatedDate":"2022-10-18T13:02:14.9707476-04:00","filePath":"D:/Unity/Unity Projects/Control Room URP/Assets/GameDevHQ/FileBase/3D/Environments/Sci-Fi/Scifi_Floors_01_12"},{"id":1184,"modifiedDate":"2021-12-31T01:14:58","fileModifiedDate":"2022-10-20T17:38:06.8617512-04:00","fileCreatedDate":"2022-10-18T13:02:14.9697502-04:00","filePath":"D:/Unity/Unity Projects/Control Room URP/Assets/GameDevHQ/FileBase/3D/Environments/Sci-Fi/Scifi_Door_Single_03"},{"id":1127,"modifiedDate":"2021-12-31T01:16:15","fileModifiedDate":"2022-10-20T17:38:07.4248694-04:00","fileCreatedDate":"2022-10-18T13:02:14.9687542-04:00","filePath":"D:/Unity/Unity Projects/Control Room URP/Assets/GameDevHQ/FileBase/3D/Environments/Sci-Fi/Scifi_Columns_01_03"},{"id":1860,"modifiedDate":"2020-05-01T00:33:52","fileModifiedDate":"2022-10-20T17:43:10.8263636-04:00","fileCreatedDate":"2022-10-20T17:43:10.3337835-04:00","filePath":"D:/Unity/Unity Projects/Control Room URP/Assets/GameDevHQ/FileBase/VFX/Particles/Environment/Fog"}]